{
    "name": "cifar10_fedavg_stream_tb",
    "resource_spec": {
        "site-1": {
            "num_of_gpus": 1,
            "mem_per_gpu_in_GiB": 1
        },
        "site-2": {
            "num_of_gpus": 1,
            "mem_per_gpu_in_GiB": 1
        },
        "site-3": {
            "num_of_gpus": 1,
            "mem_per_gpu_in_GiB": 1
        },
        "site-4": {
            "num_of_gpus": 1,
            "mem_per_gpu_in_GiB": 1
        },
        "site-5": {
            "num_of_gpus": 1,
            "mem_per_gpu_in_GiB": 1
        },
        "site-6": {
            "num_of_gpus": 1,
            "mem_per_gpu_in_GiB": 1
        },
        "site-7": {
            "num_of_gpus": 1,
            "mem_per_gpu_in_GiB": 1
        },
        "site-8": {
            "num_of_gpus": 1,
            "mem_per_gpu_in_GiB": 1
        }
    },
    "deploy_map": {
        "cifar10_fedavg_stream_tb": [
            "@ALL"
        ]
    },
    "min_clients": 4,
    "job_folder_name": "cifar10_fedavg_stream_tb",
    "submitter_name": "admin@nvidia.com",
    "submitter_org": "nvidia",
    "submitter_role": "project_admin",
    "job_id": "054c9489-bf6c-447b-a6ed-e593dad509a1",
    "submit_time": 1691852975.7651913,
    "submit_time_iso": "2023-08-12T17:09:35.765191+02:00",
    "start_time": "",
    "duration": "N/A",
    "status": "SUBMITTED",
    "schedule_history": [
        "2023-08-12 17:09:36: scheduled"
    ],
    "schedule_count": 1,
    "last_schedule_time": 1691852976.5578356
}